hi_gcp.py
hi_gcp-0.0.6.dist-info/LICENSE
hi_gcp-0.0.6.dist-info/METADATA
hi_gcp-0.0.6.dist-info/WHEEL
hi_gcp-0.0.6.dist-info/top_level.txt
hi_gcp-0.0.6.dist-info/RECORD
