Metadata-Version: 2.2
Name: hi-gcp
Version: 0.0.6
Summary: GCP Utilities for BigQuery
Home-page: https://github.com/xileven
Author: J L
Author-email: jliu5277@gmail.com
Classifier: Programming Language :: Python :: 3
Classifier: License :: OSI Approved :: MIT License
Classifier: Operating System :: OS Independent
Classifier: Development Status :: 4 - Beta
Classifier: Intended Audience :: Developers
Classifier: Topic :: Database
Classifier: Topic :: Software Development :: Libraries :: Python Modules
Requires-Python: >=3.6
License-File: LICENSE
Requires-Dist: google-cloud-bigquery>=3.27.0
Requires-Dist: google-cloud-storage>=2.18.2
Requires-Dist: pandas>=2.2.3
Requires-Dist: numpy>=2.0.2
Requires-Dist: pandas-gbq>=0.24.0
Requires-Dist: pyarrow>=18.1.0
Dynamic: author
Dynamic: author-email
Dynamic: classifier
Dynamic: description
Dynamic: description-content-type
Dynamic: home-page
Dynamic: requires-dist
Dynamic: requires-python
Dynamic: summary
